.DS_Store
muldichinese/.DS_Store
muldichinese/MulDiChinese.py
muldichinese/__init__.py
muldichinese/dimensions.py
muldichinese/features.py
muldichinese-0.3.2.dist-info/LICENSE
muldichinese-0.3.2.dist-info/METADATA
muldichinese-0.3.2.dist-info/WHEEL
muldichinese-0.3.2.dist-info/top_level.txt
muldichinese-0.3.2.dist-info/RECORD
