Metadata-Version: 2.1
Name: muldichinese
Version: 0.3.2
Summary: A Chinese register analyser.
Home-page: https://github.com/Nannan-Liu/Multidimensional-Analysis-Tagger-of-Mandarin-Chinese
Author: Nannan Liu
Author-email: liunannan.bfsumun@gmail.com
License: GNU
Keywords: muldichinese,multidimensional,register,chinese,segmentation,nlp
Platform: UNKNOWN
Classifier: Programming Language :: Python
Classifier: License :: OSI Approved :: GNU General Public License v3 (GPLv3)
Classifier: Natural Language :: Chinese (Simplified)
Classifier: Natural Language :: Chinese (Traditional)
Classifier: Operating System :: MacOS :: MacOS X
Classifier: Operating System :: Microsoft :: Windows
Classifier: Operating System :: POSIX :: Linux
Classifier: Intended Audience :: Developers
Classifier: Programming Language :: Python :: 3
Classifier: Topic :: Education
Classifier: Topic :: Text Processing :: Linguistic
Classifier: Topic :: Software Development :: Libraries :: Python Modules
Requires-Python: >=3.6
Requires-Dist: nltk
Requires-Dist: PyNLPIR
Requires-Dist: scikit-learn
Requires-Dist: numpy
Requires-Dist: pandas
